puchikarui/__init__.py
puchikarui/puchikarui.py
puchikarui-0.1a2.dist-info/LICENSE
puchikarui-0.1a2.dist-info/METADATA
puchikarui-0.1a2.dist-info/WHEEL
puchikarui-0.1a2.dist-info/top_level.txt
puchikarui-0.1a2.dist-info/RECORD
