Metadata-Version: 2.1
Name: puchikarui
Version: 0.1a2
Summary: A minimalist SQLite wrapper library for Python which supports ORM features.
Home-page: https://letuananh.github.io/puchikarui/
Author: Le Tuan Anh
Author-email: tuananh.ke@gmail.com
License: 0.1a2
Keywords: SQLite sqlite3 database
Platform: any
Classifier: Programming Language :: Python
Classifier: Development Status :: 3 - Alpha
Classifier: Natural Language :: English
Classifier: Environment :: Plugins
Classifier: Intended Audience :: Developers
Classifier: License :: OSI Approved :: MIT License
Classifier: Operating System :: OS Independent
Classifier: Topic :: Software Development :: Libraries :: Python Modules
Classifier: Topic :: Database
